risclog.logging-1.3.2-py3.9-nspkg.pth
risclog/logging/__init__.py
risclog/logging/conftest.py
risclog/logging/decorators.py
risclog/logging/log.py
risclog/logging/sender.py
risclog/logging/tests/__init__.py
risclog/logging/tests/test_logger.py
risclog/logging/tests/test_sender.py
risclog.logging-1.3.2.dist-info/AUTHORS.rst
risclog.logging-1.3.2.dist-info/LICENSE
risclog.logging-1.3.2.dist-info/METADATA
risclog.logging-1.3.2.dist-info/WHEEL
risclog.logging-1.3.2.dist-info/namespace_packages.txt
risclog.logging-1.3.2.dist-info/top_level.txt
risclog.logging-1.3.2.dist-info/RECORD
