Metadata-Version: 2.1
Name: risclog.logging
Version: 1.3.2
Summary: A logger based on structlog
Home-page: https://github.com/risclog-solution/risclog.logging
Author: riscLOG Solution GmbH
Author-email: info@risclog.de
License: MIT license
Keywords: risclog.logging
Classifier: Development Status :: 5 - Production/Stable
Classifier: Intended Audience :: Developers
Classifier: License :: OSI Approved :: MIT License
Classifier: Natural Language :: German
Classifier: Programming Language :: Python :: 3
Classifier: Programming Language :: Python :: 3.8
Classifier: Programming Language :: Python :: 3.9
Classifier: Programming Language :: Python :: 3.10
Classifier: Programming Language :: Python :: 3.11
Requires-Python: >=3.8
License-File: LICENSE
License-File: AUTHORS.rst
Requires-Dist: structlog
Provides-Extra: docs
Requires-Dist: Sphinx ; extra == 'docs'
Provides-Extra: test
Requires-Dist: pytest-cache ; extra == 'test'
Requires-Dist: pytest-cov ; extra == 'test'
Requires-Dist: pytest-flake8 ; extra == 'test'
Requires-Dist: pytest-rerunfailures ; extra == 'test'
Requires-Dist: pytest-sugar ; extra == 'test'
Requires-Dist: pytest ; extra == 'test'
Requires-Dist: coverage ; extra == 'test'
Requires-Dist: flake8 <4 ; extra == 'test'
Requires-Dist: mock ; extra == 'test'
Requires-Dist: requests ; extra == 'test'
Requires-Dist: httpx ; extra == 'test'
Requires-Dist: pytest-asyncio ; extra == 'test'
